Metadata-Version: 1.0
Name: droigo
Version: 0.2.7
Summary: Golang coding standard tools for Droi
Home-page: http://gitlab.droi.com/fxcat/golang4all
Author: Fiathux Su
Author-email: fiathux@gmail.com
License: BSD
Keywords: droigo golang
Platform: any
